setup.py
asposebarcodecloud/ApiClient.py
asposebarcodecloud/BarcodeApi.py
asposebarcodecloud/__init__.py
asposebarcodecloud.egg-info/PKG-INFO
asposebarcodecloud.egg-info/SOURCES.txt
asposebarcodecloud.egg-info/dependency_links.txt
asposebarcodecloud.egg-info/requires.txt
asposebarcodecloud.egg-info/top_level.txt
asposebarcodecloud/models/Barcode.py
asposebarcodecloud/models/BarcodeReader.py
asposebarcodecloud/models/BarcodeResponseList.py
asposebarcodecloud/models/BinarizationHints.py
asposebarcodecloud/models/ChecksumValidation.py
asposebarcodecloud/models/ResponseMessage.py
asposebarcodecloud/models/SaaSposeResponse.py
asposebarcodecloud/models/__init__.py
tests/__init__.py
tests/test_BarcodeApi.py